pygraphite/__init__.py
pygraphite/setup_custom.py
pygraphite-0.1.3.dist-info/LICENSE
pygraphite-0.1.3.dist-info/METADATA
pygraphite-0.1.3.dist-info/WHEEL
pygraphite-0.1.3.dist-info/top_level.txt
pygraphite-0.1.3.dist-info/RECORD
